mkast/__init__.py
mkast/__main__.py
mkast/__version__.py
mkast/cfg.py
mkast/cli.py
mkast/domain.py
mkast/mkast.py
mkast/py.typed
mkast/util.py
mkast/schemas/config.json
mkast/schemas/nodes.json
mkast/targets/__init__.py
mkast/targets/agnostic.py
mkast/targets/csharp.py
mkast-2.0.1.dist-info/licenses/LICENSE
mkast-2.0.1.dist-info/METADATA
mkast-2.0.1.dist-info/WHEEL
mkast-2.0.1.dist-info/entry_points.txt
mkast-2.0.1.dist-info/top_level.txt
mkast-2.0.1.dist-info/RECORD
