Metadata-Version: 2.4
Name: mkast
Version: 2.0.1
Summary: AST generator
Author-email: 5cover <thediscover22450@gmail.com>
License-Expression: Unlicense
Project-URL: Homepage, https://github.com/5cover/mkast
Project-URL: Source, https://github.com/5cover/mkast
Project-URL: Bug Reports, https://github.com/5cover/mkast/issues
Classifier: Programming Language :: Python :: 3
Requires-Python: >=3.7
License-File: LICENSE
Requires-Dist: pydantic>=2
Requires-Dist: PyYAML>=6
Dynamic: license-file
